{"timestamp": 1764506046.0822809, "source": "TRINITY_BRIDGE", "components": {"industriverse": {"kernel_load": 0.6198637550736821, "capsule_count": 435, "active_agents": 51}, "thermodynasty": {"edcoc_temp_c": 55.69462919248618, "power_draw_w": 49.29630255513649, "tensor_core_util": 0.41922926711055264}, "empeiria": {"active_experiments": 4, "hypothesis_confidence": 0.7676399036523737}}, "sync_integrity": 1.0, "thermodynamics": {"negentropy_score": 31.6878, "thermal_efficiency": 7.8104, "innovation_potential": 0.535, "unit": "J/K (Information Entropy)"}}