{"timestamp": 1764485443.315438, "source": "TRINITY_BRIDGE", "components": {"industriverse": {"kernel_load": 0.3123596762094809, "capsule_count": 205, "active_agents": 51}, "thermodynasty": {"edcoc_temp_c": 57.66278613847976, "power_draw_w": 26.34748685367302, "tensor_core_util": 0.41429110171380024}, "empeiria": {"active_experiments": 5, "hypothesis_confidence": 0.9685127971861751}}, "sync_integrity": 1.0, "thermodynamics": {"negentropy_score": 26.9867, "thermal_efficiency": 3.5552, "innovation_potential": 0.305, "unit": "J/K (Information Entropy)"}}