{"timestamp": 1764509869.6788402, "source": "TRINITY_BRIDGE", "components": {"industriverse": {"kernel_load": 0.6882945992379996, "capsule_count": 267, "active_agents": 38}, "thermodynasty": {"edcoc_temp_c": 68.57001176886851, "power_draw_w": 27.41143067662214, "tensor_core_util": 0.8685157558347388}, "empeiria": {"active_experiments": 1, "hypothesis_confidence": 0.6060701686935712}}, "sync_integrity": 1.0, "thermodynamics": {"negentropy_score": 28.4103, "thermal_efficiency": 3.8938, "innovation_potential": 0.367, "unit": "J/K (Information Entropy)"}}