{"timestamp": 1764507858.584311, "source": "TRINITY_BRIDGE", "components": {"industriverse": {"kernel_load": 0.769405762319266, "capsule_count": 302, "active_agents": 51}, "thermodynasty": {"edcoc_temp_c": 64.79628315880203, "power_draw_w": 26.53847463898977, "tensor_core_util": 0.9100653669249605}, "empeiria": {"active_experiments": 3, "hypothesis_confidence": 0.9428424623225897}}, "sync_integrity": 1.0, "thermodynamics": {"negentropy_score": 35.1246, "thermal_efficiency": 4.6608, "innovation_potential": 0.402, "unit": "J/K (Information Entropy)"}}