{"timestamp": 1764506043.204849, "source": "TRINITY_BRIDGE", "components": {"industriverse": {"kernel_load": 0.35760324746554983, "capsule_count": 421, "active_agents": 95}, "thermodynasty": {"edcoc_temp_c": 49.86233055872326, "power_draw_w": 17.328257147839143, "tensor_core_util": 0.43242473200979503}, "empeiria": {"active_experiments": 4, "hypothesis_confidence": 0.6825377413334326}}, "sync_integrity": 1.0, "thermodynamics": {"negentropy_score": 97.4506, "thermal_efficiency": 8.4432, "innovation_potential": 0.521, "unit": "J/K (Information Entropy)"}}