{"timestamp": 1764506028.438758, "source": "TRINITY_BRIDGE", "components": {"industriverse": {"kernel_load": 0.7398492894770405, "capsule_count": 345, "active_agents": 56}, "thermodynasty": {"edcoc_temp_c": 61.620748541459264, "power_draw_w": 20.961693842391874, "tensor_core_util": 0.5123995669754075}, "empeiria": {"active_experiments": 5, "hypothesis_confidence": 0.9790080988350411}}, "sync_integrity": 1.0, "thermodynamics": {"negentropy_score": 53.419, "thermal_efficiency": 5.5988, "innovation_potential": 0.445, "unit": "J/K (Information Entropy)"}}