{"timestamp": 1764509868.01632, "source": "TRINITY_BRIDGE", "components": {"industriverse": {"kernel_load": 0.22577804789898107, "capsule_count": 222, "active_agents": 12}, "thermodynasty": {"edcoc_temp_c": 51.08323330753966, "power_draw_w": 31.73205270422397, "tensor_core_util": 0.4599116559040275}, "empeiria": {"active_experiments": 2, "hypothesis_confidence": 0.5973374359030045}}, "sync_integrity": 1.0, "thermodynamics": {"negentropy_score": 27.3909, "thermal_efficiency": 4.3458, "innovation_potential": 0.322, "unit": "J/K (Information Entropy)"}}