{"timestamp": 1764506040.9475389, "source": "TRINITY_BRIDGE", "components": {"industriverse": {"kernel_load": 0.6483583399884801, "capsule_count": 480, "active_agents": 48}, "thermodynasty": {"edcoc_temp_c": 53.5352324337992, "power_draw_w": 22.571142055248757, "tensor_core_util": 0.2640835490666853}, "empeiria": {"active_experiments": 5, "hypothesis_confidence": 0.6333795202299114}}, "sync_integrity": 1.0, "thermodynamics": {"negentropy_score": 79.4471, "thermal_efficiency": 8.9661, "innovation_potential": 0.58, "unit": "J/K (Information Entropy)"}}