{"timestamp": 1764483742.3717508, "source": "TRINITY_BRIDGE", "components": {"industriverse": {"kernel_load": 0.7506009208074507, "capsule_count": 258, "active_agents": 64}, "thermodynasty": {"edcoc_temp_c": 70.19716649161128, "power_draw_w": 17.254949351332762, "tensor_core_util": 0.2817639495146474}, "empeiria": {"active_experiments": 5, "hypothesis_confidence": 0.7262485217762935}}, "sync_integrity": 1.0, "thermodynamics": {"negentropy_score": 42.6007, "thermal_efficiency": 3.6754, "innovation_potential": 0.358, "unit": "J/K (Information Entropy)"}}