{"timestamp": 1764507141.7689002, "source": "TRINITY_BRIDGE", "components": {"industriverse": {"kernel_load": 0.512729643739518, "capsule_count": 361, "active_agents": 65}, "thermodynasty": {"edcoc_temp_c": 51.063832141119974, "power_draw_w": 29.167796494623936, "tensor_core_util": 0.20059041793712085}, "empeiria": {"active_experiments": 5, "hypothesis_confidence": 0.7157801615006643}}, "sync_integrity": 1.0, "thermodynamics": {"negentropy_score": 48.4753, "thermal_efficiency": 7.0696, "innovation_potential": 0.461, "unit": "J/K (Information Entropy)"}}