{"timestamp": 1764507129.070972, "source": "TRINITY_BRIDGE", "components": {"industriverse": {"kernel_load": 0.6342015955397898, "capsule_count": 323, "active_agents": 78}, "thermodynasty": {"edcoc_temp_c": 66.05852011359629, "power_draw_w": 23.06157780656155, "tensor_core_util": 0.9253243055890583}, "empeiria": {"active_experiments": 2, "hypothesis_confidence": 0.7730782000815364}}, "sync_integrity": 1.0, "thermodynamics": {"negentropy_score": 42.4048, "thermal_efficiency": 4.8896, "innovation_potential": 0.423, "unit": "J/K (Information Entropy)"}}