{"timestamp": 1764507119.358145, "source": "TRINITY_BRIDGE", "components": {"industriverse": {"kernel_load": 0.497265155110828, "capsule_count": 460, "active_agents": 10}, "thermodynasty": {"edcoc_temp_c": 63.1281589074704, "power_draw_w": 40.40135324202136, "tensor_core_util": 0.6050918163437092}, "empeiria": {"active_experiments": 2, "hypothesis_confidence": 0.5330211194766815}}, "sync_integrity": 1.0, "thermodynamics": {"negentropy_score": 36.0719, "thermal_efficiency": 7.2868, "innovation_potential": 0.56, "unit": "J/K (Information Entropy)"}}