{"timestamp": 1764483364.790554, "source": "TRINITY_BRIDGE", "components": {"industriverse": {"kernel_load": 0.4083178978364238, "capsule_count": 491, "active_agents": 56}, "thermodynasty": {"edcoc_temp_c": 73.24423321734717, "power_draw_w": 31.562971734329448, "tensor_core_util": 0.5079643770757221}, "empeiria": {"active_experiments": 3, "hypothesis_confidence": 0.8427431584235721}}, "sync_integrity": 1.0, "thermodynamics": {"negentropy_score": 42.4776, "thermal_efficiency": 6.7036, "innovation_potential": 0.591, "unit": "J/K (Information Entropy)"}}