{
  "version": "7",
  "dialect": "mysql",
  "entries": [
    {
      "idx": 0,
      "version": "5",
      "when": 1763362188371,
      "tag": "0000_motionless_eddie_brock",
      "breakpoints": true
    },
    {
      "idx": 1,
      "version": "5",
      "when": 1763362287310,
      "tag": "0001_typical_radioactive_man",
      "breakpoints": true
    },
    {
      "idx": 2,
      "version": "5",
      "when": 1763364810614,
      "tag": "0002_zippy_arclight",
      "breakpoints": true
    }
  ]
}